osanim/__init__.py
osanim/x_one.py
osanim_one-0.0.8.dist-info/LICENSE
osanim_one-0.0.8.dist-info/METADATA
osanim_one-0.0.8.dist-info/WHEEL
osanim_one-0.0.8.dist-info/top_level.txt
osanim_one-0.0.8.dist-info/RECORD
