Metadata-Version: 2.1
Name: osanim-one
Version: 0.0.8
Summary: Business Utility Library
Home-page: https://github.com/osanim/one_py
Author: Osanim Systems
Author-email: osanimsystems@gmail.com
Project-URL: Bug Tracker, https://github.com/osanim/one_py/-/issues
Project-URL: repository, https://github.com/osanim/one_py
Classifier: Programming Language :: Python :: 3
Classifier: License :: OSI Approved :: MIT License
Classifier: Operating System :: OS Independent
Requires-Python: >=3.6
License-File: LICENSE
